coincurve/__init__.py
coincurve/_cffi_backend.cpython-313-i386-linux-gnu.so
coincurve/_libsecp256k1.cpython-313-i386-linux-gnu.so
coincurve/context.py
coincurve/der.py
coincurve/ecdsa.py
coincurve/flags.py
coincurve/keys.py
coincurve/py.typed
coincurve/types.py
coincurve/utils.py
coincurve-21.0.0.dist-info/METADATA
coincurve-21.0.0.dist-info/WHEEL
coincurve-21.0.0.dist-info/RECORD
coincurve-21.0.0.dist-info/licenses/LICENSE-APACHE
coincurve-21.0.0.dist-info/licenses/LICENSE-MIT
coincurve-21.0.0.dist-info/licenses/LICENSE-cffi
coincurve-21.0.0.dist-info/licenses/NOTICE
