Metadata-Version: 2.4
Name: coincurve
Version: 21.0.0
Summary: Safest and fastest Python library for secp256k1 elliptic curve operations
Project-URL: Homepage, https://ofek.dev/coincurve/
Project-URL: Sponsor, https://github.com/sponsors/ofek
Project-URL: History, https://ofek.dev/coincurve/history/
Project-URL: Tracker, https://github.com/ofek/coincurve/issues
Project-URL: Source, https://github.com/ofek/coincurve
Author-email: Ofek Lev <oss@ofek.dev>
License-Expression: MIT OR Apache-2.0
License-File: LICENSE-APACHE
License-File: LICENSE-MIT
License-File: NOTICE
Keywords: bitcoin,crypto,cryptocurrency,ecdh,ecdsa,elliptic curves,ethereum,libsecp256k1,schnorr,secp256k1
Classifier: Development Status :: 5 - Production/Stable
Classifier: Intended Audience :: Developers
Classifier: License :: OSI Approved :: Apache Software License
Classifier: License :: OSI Approved :: MIT License
Classifier: Natural Language :: English
Classifier: Operating System :: OS Independent
Classifier: Programming Language :: Python :: 3
Classifier: Programming Language :: Python :: 3.9
Classifier: Programming Language :: Python :: 3.10
Classifier: Programming Language :: Python :: 3.11
Classifier: Programming Language :: Python :: 3.12
Classifier: Programming Language :: Python :: 3.13
Classifier: Programming Language :: Python :: Implementation :: CPython
Classifier: Programming Language :: Python :: Implementation :: PyPy
Classifier: Topic :: Security :: Cryptography
Classifier: Topic :: Software Development :: Libraries
Requires-Python: >=3.9
